daemail/__init__.py
daemail/__main__.py
daemail/message.py
daemail/py.typed
daemail/reporter.py
daemail/runner.py
daemail/senders.py
daemail/util.py
daemail-0.7.1.dist-info/METADATA
daemail-0.7.1.dist-info/WHEEL
daemail-0.7.1.dist-info/entry_points.txt
daemail-0.7.1.dist-info/licenses/LICENSE
daemail-0.7.1.dist-info/RECORD
