Metadata-Version: 2.3
Name: daemail
Version: 0.7.1
Summary: Daemonize a command and e-mail the results
Project-URL: Source Code, https://github.com/jwodder/daemail
Project-URL: Bug Tracker, https://github.com/jwodder/daemail/issues
Author-email: John Thorvald Wodder II <daemail@varonathe.org>
License: MIT
Keywords: background,daemon,e-mail,email,mail,notifications,output,smtp
Classifier: Environment :: No Input/Output (Daemon)
Classifier: Intended Audience :: Information Technology
Classifier: Intended Audience :: System Administrators
Classifier: License :: OSI Approved :: MIT License
Classifier: Operating System :: POSIX
Classifier: Programming Language :: Python :: 3
Classifier: Programming Language :: Python :: 3 :: Only
Classifier: Programming Language :: Python :: 3.8
Classifier: Programming Language :: Python :: 3.9
Classifier: Programming Language :: Python :: 3.10
Classifier: Programming Language :: Python :: 3.11
Classifier: Programming Language :: Python :: 3.12
Classifier: Programming Language :: Python :: 3.13
Classifier: Programming Language :: Python :: Implementation :: CPython
Classifier: Programming Language :: Python :: Implementation :: PyPy
Classifier: Topic :: Communications :: Email
Classifier: Topic :: Utilities
Classifier: Typing :: Typed
Requires-Python: >=3.8
Requires-Dist: attrs>=18.1
Requires-Dist: click>=7.0
Requires-Dist: eletter~=0.4
Requires-Dist: mailbits~=0.2
Requires-Dist: morecontext>=0.4.1
Requires-Dist: outgoing~=0.2
Requires-Dist: python-daemon<4.0,>=2.0
